{
  "port": "KdeBase-Main",
  "name": "Kconfigwidgets",
  "version": "5.85.0",
  "architectures": [
    "x86_64"
  ],
  "description": "Widgets for configuration dialogs",
  "website": "https://api.kde.org/frameworks/kconfigwidgets/html/index.html",
  "installedFiles": [],
  "dependencies": [
    {
      "name": "Extra-Cmake-Modules",
      "version": ">=5.85.0",
      "options": []
    },
    {
      "name": "Qt",
      "version": "5.15.2",
      "options": []
    }
  ],
  "kernelDependencies": [],
  "options": [],
  "uniqueOptions": []
}
