{
  "port": "KdeBase-Main",
  "name": "Kparts",
  "version": "5.109.0",
  "architectures": ["x86_64"],
  "description": "Plugin framework for user interface components",
  "website": "https://api.kde.org/frameworks/kparts/html/index.html",
  "installedFiles": [],
  "dependencies": [
    {
      "port": "ProgrammingTools-Main",
      "name": "Extra-Cmake-Modules",
      "version": ">=5.0.0 ~ <6.0.0",
      "options": []
    },
    {
      "port": "QtLibraries-Main",
      "name": "Qtbase",
      "version": ">=5.0.0 ~ <6.0.0",
      "options": []
    },
    {
      "port": "KdeBase-Main",
      "name": "Kio",
      "version": ">=5.0.0 ~ <6.0.0",
      "options": []
    }
  ],
  "kernelDependencies": [],
  "options": [],
  "uniqueDependencies": [],
  "uniqueOptions": [],
  "selectedDependencies": [],
  "allowCodependencies": []
}
